gym_staticinvader/__init__.py
gym_staticinvader/envs/__init__.py
gym_staticinvader/envs/staticinvader_env.py
gym_staticinvader/envs/staticinvader_extrahard_env.py
gym_staticinvader-0.0.2.dist-info/LICENSE
gym_staticinvader-0.0.2.dist-info/METADATA
gym_staticinvader-0.0.2.dist-info/WHEEL
gym_staticinvader-0.0.2.dist-info/top_level.txt
gym_staticinvader-0.0.2.dist-info/RECORD
