Metadata-Version: 2.1
Name: gym-staticinvader
Version: 0.0.2
Summary: A small example package
Home-page: https://github.com/VivianoRiccardo/gym_environment_test
Author: Riccardo Viviano
Author-email: riciric83@gmail.com
License: UNKNOWN
Platform: UNKNOWN
Classifier: Programming Language :: Python :: 3
Classifier: License :: OSI Approved :: MIT License
Classifier: Operating System :: OS Independent
Requires-Python: >=3.5.2
Requires-Dist: gym
Requires-Dist: numpy
